<rows>
<SYSQVFORMATCONDITION__C>
	<ID>id</ID>
	<ISDELETED>boolean</ISDELETED>
	<NAME>string</NAME>
	<CREATEDDATE>datetime</CREATEDDATE>
	<CREATEDBYID>reference</CREATEDBYID>
	<LASTMODIFIEDDATE>datetime</LASTMODIFIEDDATE>
	<LASTMODIFIEDBYID>reference</LASTMODIFIEDBYID>
	<SYSTEMMODSTAMP>datetime</SYSTEMMODSTAMP>
	<SYSQVFORMATRULE__C>reference</SYSQVFORMATRULE__C>
	<ORDERINDEX__C>string</ORDERINDEX__C>
	<SYSQVFIELDINFO__C>reference</SYSQVFIELDINFO__C>
	<SEQUENCE__C>string</SEQUENCE__C>
	<SYSQVLOGICALOPERATOR__C>string</SYSQVLOGICALOPERATOR__C>
	<SYSQVOPERATOR__C>string</SYSQVOPERATOR__C>
	<VALUES__C>string</VALUES__C>
</SYSQVFORMATCONDITION__C>
<row>
  <SYSQVFORMATRULE__C>1</SYSQVFORMATRULE__C>
  <ORDERINDEX__C></ORDERINDEX__C>
  <SYSQVFIELDINFO__C>1</SYSQVFIELDINFO__C>
  <SEQUENCE__C>1</SEQUENCE__C>
  <SYSQVLOGICALOPERATOR__C></SYSQVLOGICALOPERATOR__C>
  <SYSQVOPERATOR__C>=</SYSQVOPERATOR__C>
  <VALUES__C>1</VALUES__C>
</row>
<row>
  <SYSQVFORMATRULE__C>2</SYSQVFORMATRULE__C>
  <ORDERINDEX__C></ORDERINDEX__C>
  <SYSQVFIELDINFO__C>1</SYSQVFIELDINFO__C>
  <SEQUENCE__C>2</SEQUENCE__C>
  <SYSQVLOGICALOPERATOR__C></SYSQVLOGICALOPERATOR__C>
  <SYSQVOPERATOR__C>=</SYSQVOPERATOR__C>
  <VALUES__C>2</VALUES__C>
</row>
<row>
  <SYSQVFORMATRULE__C>3</SYSQVFORMATRULE__C>
  <ORDERINDEX__C></ORDERINDEX__C>
  <SYSQVFIELDINFO__C>1</SYSQVFIELDINFO__C>
  <SEQUENCE__C>3</SEQUENCE__C>
  <SYSQVLOGICALOPERATOR__C></SYSQVLOGICALOPERATOR__C>
  <SYSQVOPERATOR__C>=</SYSQVOPERATOR__C>
  <VALUES__C>3</VALUES__C>
</row>
<row>
  <SYSQVFORMATRULE__C>4</SYSQVFORMATRULE__C>
  <ORDERINDEX__C></ORDERINDEX__C>
  <SYSQVFIELDINFO__C>21</SYSQVFIELDINFO__C>
  <SEQUENCE__C>4</SEQUENCE__C>
  <SYSQVLOGICALOPERATOR__C></SYSQVLOGICALOPERATOR__C>
  <SYSQVOPERATOR__C>=</SYSQVOPERATOR__C>
  <VALUES__C>1</VALUES__C>
</row>
<row>
  <SYSQVFORMATRULE__C>5</SYSQVFORMATRULE__C>
  <ORDERINDEX__C></ORDERINDEX__C>
  <SYSQVFIELDINFO__C>21</SYSQVFIELDINFO__C>
  <SEQUENCE__C>5</SEQUENCE__C>
  <SYSQVLOGICALOPERATOR__C></SYSQVLOGICALOPERATOR__C>
  <SYSQVOPERATOR__C>=</SYSQVOPERATOR__C>
  <VALUES__C>2</VALUES__C>
</row>
<row>
  <SYSQVFORMATRULE__C>6</SYSQVFORMATRULE__C>
  <ORDERINDEX__C></ORDERINDEX__C>
  <SYSQVFIELDINFO__C>21</SYSQVFIELDINFO__C>
  <SEQUENCE__C>6</SEQUENCE__C>
  <SYSQVLOGICALOPERATOR__C></SYSQVLOGICALOPERATOR__C>
  <SYSQVOPERATOR__C>=</SYSQVOPERATOR__C>
  <VALUES__C>3</VALUES__C>
</row>
<row>
  <SYSQVFORMATRULE__C>7</SYSQVFORMATRULE__C>
  <ORDERINDEX__C></ORDERINDEX__C>
  <SYSQVFIELDINFO__C>352</SYSQVFIELDINFO__C>
  <SEQUENCE__C>7</SEQUENCE__C>
  <SYSQVLOGICALOPERATOR__C></SYSQVLOGICALOPERATOR__C>
  <SYSQVOPERATOR__C>=</SYSQVOPERATOR__C>
  <VALUES__C>0</VALUES__C>
</row>
<row>
  <SYSQVFORMATRULE__C>8</SYSQVFORMATRULE__C>
  <ORDERINDEX__C></ORDERINDEX__C>
  <SYSQVFIELDINFO__C>352</SYSQVFIELDINFO__C>
  <SEQUENCE__C>8</SEQUENCE__C>
  <SYSQVLOGICALOPERATOR__C></SYSQVLOGICALOPERATOR__C>
  <SYSQVOPERATOR__C>&lt;=</SYSQVOPERATOR__C>
  <VALUES__C>50</VALUES__C>
</row>
</rows>